{
    "title": "Twitter",
    "items": [
        {
            "title": "Luke Gorrie",
            "twitter_user": "lukego",
            "twitter_id": "362022429"
        },
        {
            "title": "Elon Musk",
            "twitter_user": "elonmusk",
            "twitter_id": "44196397"
        },
        {
            "title": "William MacAskill",
            "twitter_user": "willmacaskill",
            "twitter_id": "363005534"
        },        
        {
            "title": "Stephanie Kelton",
            "twitter_user": "stephaniekelton",
            "twitter_id": "334217161"
        },
        {
            "title": "Erik Vance",
            "twitter_user": "erikvance",
            "twitter_id": "21441341"
        },
        {
            "title": "Open Sauced",
            "twitter_user": "saucedopen",
            "twitter_id": "1093021363512569857"
        }
    ]
}
